assistant_lib/__init__.py
assistant_lib/assistant.py
assistant_lib/jsonlogger.py
assistant_lib-0.16.dist-info/LICENSE
assistant_lib-0.16.dist-info/METADATA
assistant_lib-0.16.dist-info/WHEEL
assistant_lib-0.16.dist-info/top_level.txt
assistant_lib-0.16.dist-info/RECORD
