Metadata-Version: 2.1
Name: assistant-lib
Version: 0.16
Summary: The Assistant python library
Home-page: https://gitlab.com/goassistant/assistant-client-python
Author: Fritz
Author-email: fritz.smh@gmail.com
License: UNKNOWN
Platform: UNKNOWN
Classifier: Programming Language :: Python :: 3
Classifier: License :: OSI Approved :: GNU Lesser General Public License v3 (LGPLv3)
Classifier: Operating System :: OS Independent
Requires-Python: >=3.6
Requires-Dist: python-json-logger
